sejong_univ_auth/__init__.py
sejong_univ_auth/auth.py
sejong_univ_auth/config.py
sejong_univ_auth/decorator.py
sejong_univ_auth/exceptions.py
sejong_univ_auth/legacy.py
sejong_univ_auth/method.py
sejong_univ_auth/authenticator/__init__.py
sejong_univ_auth/authenticator/classic_session.py
sejong_univ_auth/authenticator/dosejong_session.py
sejong_univ_auth/authenticator/moodler_session.py
sejong_univ_auth/authenticator/portal_ssotoken.py
sejong_univ_auth-0.3.4.dist-info/LICENSE
sejong_univ_auth-0.3.4.dist-info/METADATA
sejong_univ_auth-0.3.4.dist-info/WHEEL
sejong_univ_auth-0.3.4.dist-info/top_level.txt
sejong_univ_auth-0.3.4.dist-info/RECORD
