Metadata-Version: 2.1
Name: sejong-univ-auth
Version: 0.3.4
Summary: Sejong University Member Account Authentication.
Home-page: https://github.com/iml1111/sejong-univ-auth
Author: IML
Author-email: shin10256@gmail.com
License: MIT
Keywords: sejong univ auth
Platform: any
Classifier: Intended Audience :: Developers
Classifier: License :: OSI Approved :: MIT License
Classifier: Operating System :: OS Independent
Classifier: Programming Language :: Python :: 3.7
Classifier: Programming Language :: Python :: 3.8
Classifier: Programming Language :: Python :: 3.9
Classifier: Topic :: Internet :: WWW/HTTP :: Dynamic Content
Classifier: Topic :: Software Development :: Libraries :: Python Modules
License-File: LICENSE
